component/__init__.py
component/main.py
roman_number_converter-1.0.0.dist-info/METADATA
roman_number_converter-1.0.0.dist-info/WHEEL
roman_number_converter-1.0.0.dist-info/top_level.txt
roman_number_converter-1.0.0.dist-info/RECORD
