Metadata-Version: 2.1
Name: roman-number-converter
Version: 1.0.0
Summary: Component for converting Roman numbers to arabic and vice versa.
Home-page: https://github.com/daiarn/RomanConverter
Author: Dainius Arnastauskas
Author-email: dainius1997@gmail.com
License: MIT
Platform: UNKNOWN
Classifier: License :: OSI Approved :: MIT License
Classifier: Programming Language :: Python :: 3
Classifier: Programming Language :: Python :: 3.9
